schd/__init__.py
schd/config.py
schd/email.py
schd/job.py
schd/scheduler.py
schd/util.py
schd/cmds/__init__.py
schd/cmds/addtrigger.py
schd/cmds/base.py
schd/cmds/daemon.py
schd/cmds/jobs.py
schd/cmds/run.py
schd/cmds/schd.py
schd/cmds/scsendmail.py
schd/schedulers/__init__.py
schd/schedulers/remote.py
schd-0.2.0.dist-info/METADATA
schd-0.2.0.dist-info/WHEEL
schd-0.2.0.dist-info/entry_points.txt
schd-0.2.0.dist-info/top_level.txt
schd-0.2.0.dist-info/RECORD
