Metadata-Version: 2.4
Name: schd
Version: 0.2.0
Home-page: https://github.com/kevenli/schd
License: ApacheV2
Requires-Dist: apscheduler<4.0
Requires-Dist: pyaml
Requires-Dist: aiohttp
Dynamic: home-page
Dynamic: license
Dynamic: requires-dist
